{
  "commands": [
    { "type": "addVehicle", "vehicleId": "carA", "startRoad": "north", "endRoad": "south" },
    { "type": "addVehicle", "vehicleId": "carB", "startRoad": "north", "endRoad": "east" },
    { "type": "addPedestrian", "pedestrianId": "pA", "startRoad": "north", "endRoad": "east" },
    { "type": "step" },
    { "type": "addVehicle", "vehicleId": "carC", "startRoad": "east", "endRoad": "north" },
    { "type": "addPedestrian", "pedestrianId": "pB", "startRoad": "east", "endRoad": "south" },
    { "type": "addVehicle", "vehicleId": "carD", "startRoad": "south", "endRoad": "north" },
    { "type": "step" },
    { "type": "addPedestrian", "pedestrianId": "pC", "startRoad": "south", "endRoad": "east" },
    { "type": "addVehicle", "vehicleId": "carE", "startRoad": "west", "endRoad": "north" },
    { "type": "addPedestrian", "pedestrianId": "pD", "startRoad": "west", "endRoad": "south" },
    { "type": "step" },
    { "type": "addVehicle", "vehicleId": "carF", "startRoad": "north", "endRoad": "west" },
    { "type": "addVehicle", "vehicleId": "carG", "startRoad": "east", "endRoad": "west" },
    { "type": "step" },
    { "type": "addPedestrian", "pedestrianId": "pE", "startRoad": "south", "endRoad": "west" },
    { "type": "addPedestrian", "pedestrianId": "pF", "startRoad": "north", "endRoad": "south" },
    { "type": "step" },
    { "type": "addVehicle", "vehicleId": "carH", "startRoad": "west", "endRoad": "east" },
    { "type": "addPedestrian", "pedestrianId": "pG", "startRoad": "east", "endRoad": "north" },
    { "type": "step" },
    { "type": "addVehicle", "vehicleId": "carI", "startRoad": "south", "endRoad": "east" },
    { "type": "addPedestrian", "pedestrianId": "pH", "startRoad": "south", "endRoad": "north" },
    { "type": "step" },
    { "type": "addVehicle", "vehicleId": "carJ", "startRoad": "north", "endRoad": "east" },
    { "type": "addPedestrian", "pedestrianId": "pI", "startRoad": "north", "endRoad": "west" },
    { "type": "step" },
    { "type": "addVehicle", "vehicleId": "carK", "startRoad": "east", "endRoad": "south" },
    { "type": "addPedestrian", "pedestrianId": "pJ", "startRoad": "east", "endRoad": "north" },
    { "type": "step" },
    { "type": "addVehicle", "vehicleId": "carL", "startRoad": "west", "endRoad": "north" },
    { "type": "addPedestrian", "pedestrianId": "pK", "startRoad": "west", "endRoad": "south" },
    { "type": "step" },
    { "type": "addVehicle", "vehicleId": "carM", "startRoad": "south", "endRoad": "east" },
    { "type": "step" }
  ]
}
